<annotation>
	<folder>images</folder>
	<filename>image0070.jpg</filename>
	<path>C:\Users\Ryan\Desktop\BasketballPlayerDetection\training_set\images\image0070.jpg</path>
	<source>
		<database>Unknown</database>
	</source>
	<size>
		<width>1280</width>
		<height>720</height>
		<depth>3</depth>
	</size>
	<segmented>0</segmented>
	<object>
		<name>jazz</name>
		<pose>Unspecified</pose>
		<truncated>0</truncated>
		<difficult>0</difficult>
		<bndbox>
			<xmin>54</xmin>
			<ymin>311</ymin>
			<xmax>142</xmax>
			<ymax>537</ymax>
		</bndbox>
	</object>
	<object>
		<name>jazz</name>
		<pose>Unspecified</pose>
		<truncated>0</truncated>
		<difficult>0</difficult>
		<bndbox>
			<xmin>273</xmin>
			<ymin>250</ymin>
			<xmax>342</xmax>
			<ymax>385</ymax>
		</bndbox>
	</object>
	<object>
		<name>jazz</name>
		<pose>Unspecified</pose>
		<truncated>0</truncated>
		<difficult>0</difficult>
		<bndbox>
			<xmin>909</xmin>
			<ymin>163</ymin>
			<xmax>969</xmax>
			<ymax>291</ymax>
		</bndbox>
	</object>
	<object>
		<name>lakers</name>
		<pose>Unspecified</pose>
		<truncated>0</truncated>
		<difficult>0</difficult>
		<bndbox>
			<xmin>312</xmin>
			<ymin>320</ymin>
			<xmax>414</xmax>
			<ymax>506</ymax>
		</bndbox>
	</object>
	<object>
		<name>lakers</name>
		<pose>Unspecified</pose>
		<truncated>0</truncated>
		<difficult>0</difficult>
		<bndbox>
			<xmin>500</xmin>
			<ymin>232</ymin>
			<xmax>568</xmax>
			<ymax>427</ymax>
		</bndbox>
	</object>
	<object>
		<name>lakers</name>
		<pose>Unspecified</pose>
		<truncated>0</truncated>
		<difficult>0</difficult>
		<bndbox>
			<xmin>895</xmin>
			<ymin>185</ymin>
			<xmax>950</xmax>
			<ymax>371</ymax>
		</bndbox>
	</object>
	<object>
		<name>lakers</name>
		<pose>Unspecified</pose>
		<truncated>0</truncated>
		<difficult>0</difficult>
		<bndbox>
			<xmin>1004</xmin>
			<ymin>321</ymin>
			<xmax>1073</xmax>
			<ymax>552</ymax>
		</bndbox>
	</object>
	<object>
		<name>lakers</name>
		<pose>Unspecified</pose>
		<truncated>0</truncated>
		<difficult>0</difficult>
		<bndbox>
			<xmin>1081</xmin>
			<ymin>354</ymin>
			<xmax>1169</xmax>
			<ymax>574</ymax>
		</bndbox>
	</object>
</annotation>
